dumb_datasets/__init__.py
dumb_datasets/__version__.py
dumb_datasets/adapters.py
dumb_datasets/api.py
dumb_datasets/config.py
dumb_datasets/examples.py
dumb_datasets/exceptions.py
dumb_datasets/features.py
dumb_datasets/hooks.py
dumb_datasets/hub.py
dumb_datasets/models.py
dumb_datasets/py.typed
dumb_datasets/sessions.py
dumb_datasets/transfer.py
dumb_datasets/utils.py
dumb_datasets-0.0.2.dist-info/LICENSE
dumb_datasets-0.0.2.dist-info/METADATA
dumb_datasets-0.0.2.dist-info/WHEEL
dumb_datasets-0.0.2.dist-info/RECORD
