Metadata-Version: 2.1
Name: dumb-datasets
Version: 0.0.2
Summary: A lightweight wrapper around HuggingFace datasets.
Home-page: https://github.com/nlile/dumb-datasets
Author: nlile
Author-email: 7707104+nlile@users.noreply.github.com
Requires-Python: >=3.9,<3.13
Classifier: Programming Language :: Python :: 3
Classifier: Programming Language :: Python :: 3.9
Classifier: Programming Language :: Python :: 3.10
Classifier: Programming Language :: Python :: 3.11
Classifier: Programming Language :: Python :: 3.12
Requires-Dist: datasets (>=2.16.0,<3.0.0)
Requires-Dist: hf-transfer (>=0.1.9,<0.2.0)
Requires-Dist: huggingface-hub (>=0.29.3,<0.30.0)
Requires-Dist: litellm (>=1.63.14,<2.0.0)
Requires-Dist: loguru (>=0.7.2,<0.8.0)
Requires-Dist: numpy (>=1.23.5,<2.0.0)
Requires-Dist: pandas (>=1.5.3,<2.0.0)
Requires-Dist: pydantic (>=2.5.0,<3.0.0)
Requires-Dist: python-dotenv (>=1.0.0,<2.0.0)
Requires-Dist: tenacity (>=8.2.3,<9.0.0)
Requires-Dist: types-setuptools (>=67.8.0,<68.0.0) ; python_version >= "3.9" and python_version < "4.0"
Project-URL: Documentation, https://nlile.github.io/dumb-datasets/
Project-URL: Repository, https://github.com/nlile/dumb-datasets
